azureml/__init__.py
azureml/mlflow/__init__.py
azureml/mlflow/_version.py
azureml/mlflow/entry_point_loaders.py
azureml/mlflow/_client/__init__.py
azureml/mlflow/_client/constants.py
azureml/mlflow/_client/_common/__init__.py
azureml/mlflow/_client/_common/_http_policy.py
azureml/mlflow/_client/artifact/__init__.py
azureml/mlflow/_client/artifact/base_artifact_client.py
azureml/mlflow/_client/artifact/local_artifact_client.py
azureml/mlflow/_client/artifact/registry_artifact_client.py
azureml/mlflow/_client/artifact/registry_client.py
azureml/mlflow/_client/artifact/run_artifact_client.py
azureml/mlflow/_client/artifact/_utils/__init__.py
azureml/mlflow/_client/artifact/_utils/asset_utils.py
azureml/mlflow/_client/artifact/_utils/blob_artifact_util.py
azureml/mlflow/_client/artifact/_utils/file_utils.py
azureml/mlflow/_common/__init__.py
azureml/mlflow/_common/constants.py
azureml/mlflow/_common/exceptions.py
azureml/mlflow/_common/_authentication/__init__.py
azureml/mlflow/_common/_authentication/_arcadia_token_wrapper.py
azureml/mlflow/_common/_authentication/arcadia_authentication.py
azureml/mlflow/_common/_authentication/azureml_token_authentication.py
azureml/mlflow/_common/_authentication/databricks_cluster_authentication.py
azureml/mlflow/_common/_cloud/__init__.py
azureml/mlflow/_common/_cloud/cloud.py
azureml/mlflow/_common/_core_user_error/__init__.py
azureml/mlflow/_common/_core_user_error/user_error.py
azureml/mlflow/_common/_error_definition/__init__.py
azureml/mlflow/_common/_error_definition/azureml_error.py
azureml/mlflow/_common/_error_definition/error_definition.py
azureml/mlflow/_common/_error_definition/error_strings.py
azureml/mlflow/_common/_error_definition/user_error.py
azureml/mlflow/_common/_error_definition/utils/__init__.py
azureml/mlflow/_common/_error_definition/utils/error_decorator.py
azureml/mlflow/_common/_error_response/__init__.py
azureml/mlflow/_common/_error_response/_error_response_constants.py
azureml_mlflow-1.61.0.post1.dist-info/licenses/LICENSE.txt
azureml_mlflow-1.61.0.post1.dist-info/METADATA
azureml_mlflow-1.61.0.post1.dist-info/WHEEL
azureml_mlflow-1.61.0.post1.dist-info/entry_points.txt
azureml_mlflow-1.61.0.post1.dist-info/top_level.txt
azureml_mlflow-1.61.0.post1.dist-info/RECORD
