Metadata-Version: 2.4
Name: azureml-mlflow
Version: 1.61.0.post1
Summary: Contains the integration code of AzureML with Mlflow.
Home-page: https://docs.microsoft.com/python/api/overview/azure/ml/?view=azure-ml-py
Author: Microsoft Corp
License: https://aka.ms/azureml-sdk-license
Classifier: Development Status :: 4 - Beta
Classifier: Intended Audience :: Developers
Classifier: Intended Audience :: Science/Research
Classifier: License :: Other/Proprietary License
Classifier: Programming Language :: Python :: 3
Classifier: Programming Language :: Python :: 3.8
Classifier: Programming Language :: Python :: 3.9
Classifier: Programming Language :: Python :: 3.10
Classifier: Programming Language :: Python :: 3.11
Classifier: Topic :: Scientific/Engineering :: Artificial Intelligence
Classifier: Operating System :: Microsoft :: Windows
Classifier: Operating System :: MacOS
Classifier: Operating System :: POSIX :: Linux
Requires-Python: >=3.8,<4.0
License-File: LICENSE.txt
Requires-Dist: jsonpickle<5.0.0
Requires-Dist: mlflow-skinny<=3.5.0
Requires-Dist: azure-identity
Requires-Dist: msrest>=0.6.18
Requires-Dist: azure-core!=1.22.0,<2.0.0,>=1.8.0
Requires-Dist: azure-mgmt-core<2.0.0,>=1.2.0
Requires-Dist: azure-storage-blob<=12.19.0,>=12.5.0
Requires-Dist: azure-common<2.0.0,>=1.1
Requires-Dist: cryptography<46.0.0
Requires-Dist: python-dateutil<3.0.0,>=2.7.3
Requires-Dist: pytz<=2025.2
Provides-Extra: deployments
Requires-Dist: flask; extra == "deployments"
Requires-Dist: numpy; extra == "deployments"
Requires-Dist: pandas; extra == "deployments"
Dynamic: author
Dynamic: classifier
Dynamic: description
Dynamic: description-content-type
Dynamic: home-page
Dynamic: license
Dynamic: license-file
Dynamic: provides-extra
Dynamic: requires-dist
Dynamic: requires-python
Dynamic: summary
